huesdk/__init__.py
huesdk/discover.py
huesdk/generics.py
huesdk/group.py
huesdk/huesdk.py
huesdk/light.py
huesdk/schedule.py
huesdk-1.8.dist-info/LICENSE
huesdk-1.8.dist-info/METADATA
huesdk-1.8.dist-info/WHEEL
huesdk-1.8.dist-info/top_level.txt
huesdk-1.8.dist-info/RECORD
