Metadata-Version: 2.1
Name: huesdk
Version: 1.8
Summary: A python SDK for the Philips hue API
Home-page: https://github.com/AlexisGomes/huesdk
Author: Gomes Alexis
Author-email: alexis.gomes19@gmail.com
Classifier: Programming Language :: Python :: 3
Classifier: License :: OSI Approved :: MIT License
Classifier: Operating System :: OS Independent
License-File: LICENSE
Requires-Dist: requests
Requires-Dist: zeroconf
